sleepchunk/LICENSE
sleepchunk/README.MD
sleepchunk/__init__.py
sleepchunk/requirements.txt
sleepchunk/thirdparty.json
sleepchunk-0.10.dist-info/LICENSE.rst
sleepchunk-0.10.dist-info/METADATA
sleepchunk-0.10.dist-info/WHEEL
sleepchunk-0.10.dist-info/top_level.txt
sleepchunk-0.10.dist-info/RECORD
